recursive_sgd/__init__.py
recursive_sgd/cli.py
recursive_sgd/layers.py
recursive_sgd/losses.py
recursive_sgd/model.py
recursive_sgd/save.py
recursive_sgd/sgd.py
recursive_sgd-0.5.dist-info/LICENSE
recursive_sgd-0.5.dist-info/METADATA
recursive_sgd-0.5.dist-info/WHEEL
recursive_sgd-0.5.dist-info/entry_points.txt
recursive_sgd-0.5.dist-info/top_level.txt
recursive_sgd-0.5.dist-info/RECORD
