Metadata-Version: 2.1
Name: recursive-sgd
Version: 0.5
Summary: Train a neural network - with recursion!
Home-page: https://github.com/InCogNiTo124/recursive-sgd/
Author: Marijan Smetko
Author-email: marijan.smetko@gmail.com
License: UNKNOWN
Platform: UNKNOWN
Requires-Python: >=3.4
Requires-Dist: numpy (>=1.17)
